<?xml version="1.0" encoding="UTF-8"?>
<root>
  <instruction text="the first block from the right in front of the robot"/>
  <image file="world_0014_0004.png"/>
  <world time="0">
    <object name="O1-cube-cube-base" type="block" position="0.91004,-0.449986,0.737726" orientation="-5.34691e-06,1.44148e-05,0.00090925,1" color="na"/>
    <object name="O2-cube-cube-base" type="block" position="0.967068,-0.299984,0.737723" orientation="-6.14664e-06,1.12538e-05,3.03574e-05,1" color="na"/>
    <object name="O3-cube-cube-base" type="block" position="0.934552,-0.149982,0.737722" orientation="-6.16987e-06,1.40146e-05,-0.000465643,1" color="na"/>
    <object name="O4-cube-cube-base" type="block" position="0.87235,6.02768e-06,0.737722" orientation="-4.04025e-06,1.40217e-05,4.804e-05,1" color="na"/>
    <object name="O5-cube-cube-base" type="block" position="0.909267,0.149983,0.73772" orientation="-5.34784e-06,1.40527e-05,-0.0011179,0.999999" color="na"/>
    <object name="O6-cube-cube-base" type="block" position="0.914245,0.3,0.737718" orientation="-6.37736e-06,1.4442e-05,-0.00119039,0.999999" color="na"/>
    <object name="O7-cube-cube-base" type="block" position="0.900302,0.45006,0.737717" orientation="-4.66191e-06,1.3325e-05,0.00055367,1" color="na"/>
    <object name="baxter1-baxter-left_hand" type="robot" position="0.667324,1.07973,1.2272" orientation="-0.299912,0.646242,0.295795,0.63634" color="na"/>
    <object name="baxter1-baxter-right_hand" type="robot" position="0.8343,-0.897542,1.22895" orientation="0.24426,0.668472,-0.241448,0.659686" color="na"/>
    <object name="table-table-table-base" type="table" position="0.874999,-4.50805e-07,-0.0117897" orientation="-5.48311e-06,1.36336e-05,4.60023e-07,1" color="na"/>
  </world>
  <NP>
    <grounding>
      <grounding_set>
        <object name="O1-cube-cube-base" type="block" position="0.91004,-0.449986,0.737726" orientation="-5.34691e-06,1.44148e-05,0.00090925,1" color="na"/>
      </grounding_set>
    </grounding>
    <NP>
      <grounding>
        <grounding_set>
          <object name="O1-cube-cube-base" type="block" position="0.91004,-0.449986,0.737726" orientation="-5.34691e-06,1.44148e-05,0.00090925,1" color="na"/>
          <object_property object_type="block" relation_type="right" index="first"/>
        </grounding_set>
      </grounding>
      <NP>
        <grounding>
          <grounding_set>
            <object_property object_type="block" relation_type="na" index="first"/> 
            <object_type type="block"/>
            <index type="first"/>
          </grounding_set>
        </grounding>
        <DT text="the" order="0"/>
        <JJ text="first" order="1"/>
        <NN text="block" order="2"/>
      </NP>
      <PP>
        <grounding>
          <grounding_set>
            <spatial_relation type="right"/>
          </grounding_set>
        </grounding>
        <IN text="from" order="3"/>
        <NP>
          <grounding>
            <grounding_set>
              <spatial_relation type="right"/>
            </grounding_set>
          </grounding>
          <DT text="the" order="4"/>
          <NN text="right" order="5"/>
        </NP>
      </PP>
    </NP>
    <PP>
      <grounding>
        <grounding_set>
          <region_container type="front">
            <container type="robot">
              <object name="baxter1-baxter-left_hand" type="robot" position="0.667324,1.07973,1.2272" orientation="-0.299912,0.646242,0.295795,0.63634" color="na"/>
              <object name="baxter1-baxter-right_hand" type="robot" position="0.8343,-0.897542,1.22895" orientation="0.24426,0.668472,-0.241448,0.659686" color="na"/>
            </container>
          </region_container>
          <object name="baxter1-baxter-left_hand" type="robot" position="0.667324,1.07973,1.2272" orientation="-0.299912,0.646242,0.295795,0.63634" color="na"/>
          <object name="baxter1-baxter-right_hand" type="robot" position="0.8343,-0.897542,1.22895" orientation="0.24426,0.668472,-0.241448,0.659686" color="na"/>
        </grounding_set>
      </grounding>
      <IN text="in" order="6"/>
      <NP>
        <grounding>
          <grounding_set>
            <region_container type="front">
              <container type="robot">
                <object name="baxter1-baxter-left_hand" type="robot" position="0.667324,1.07973,1.2272" orientation="-0.299912,0.646242,0.295795,0.63634" color="na"/>
                <object name="baxter1-baxter-right_hand" type="robot" position="0.8343,-0.897542,1.22895" orientation="0.24426,0.668472,-0.241448,0.659686" color="na"/>
              </container>
            </region_container>
            <object name="baxter1-baxter-left_hand" type="robot" position="0.667324,1.07973,1.2272" orientation="-0.299912,0.646242,0.295795,0.63634" color="na"/>
            <object name="baxter1-baxter-right_hand" type="robot" position="0.8343,-0.897542,1.22895" orientation="0.24426,0.668472,-0.241448,0.659686" color="na"/>
          </grounding_set>
        </grounding>
        <NP>
          <grounding>
            <grounding_set>
              <spatial_relation type="front"/>
            </grounding_set>
          </grounding>
          <NN text="front" order="7"/>
        </NP>
        <PP>
          <grounding>
            <grounding_set>
              <container type="robot">
                <object name="baxter1-baxter-left_hand" type="robot" position="0.667324,1.07973,1.2272" orientation="-0.299912,0.646242,0.295795,0.63634" color="na"/>
                <object name="baxter1-baxter-right_hand" type="robot" position="0.8343,-0.897542,1.22895" orientation="0.24426,0.668472,-0.241448,0.659686" color="na"/>
              </container>
              <object name="baxter1-baxter-left_hand" type="robot" position="0.667324,1.07973,1.2272" orientation="-0.299912,0.646242,0.295795,0.63634" color="na"/>
              <object name="baxter1-baxter-right_hand" type="robot" position="0.8343,-0.897542,1.22895" orientation="0.24426,0.668472,-0.241448,0.659686" color="na"/>
            </grounding_set>
          </grounding>
          <IN text="of" order="8"/>
          <NP>
            <grounding>
              <grounding_set>
                <container type="robot">
                  <object name="baxter1-baxter-left_hand" type="robot" position="0.667324,1.07973,1.2272" orientation="-0.299912,0.646242,0.295795,0.63634" color="na"/>
                  <object name="baxter1-baxter-right_hand" type="robot" position="0.8343,-0.897542,1.22895" orientation="0.24426,0.668472,-0.241448,0.659686" color="na"/>
                </container>
                <object name="baxter1-baxter-left_hand" type="robot" position="0.667324,1.07973,1.2272" orientation="-0.299912,0.646242,0.295795,0.63634" color="na"/>
                <object name="baxter1-baxter-right_hand" type="robot" position="0.8343,-0.897542,1.22895" orientation="0.24426,0.668472,-0.241448,0.659686" color="na"/>
              </grounding_set>
            </grounding>
            <DT text="the" order="9"/>
            <NN text="robot" order="10"/>
          </NP>
        </PP>
      </NP>
    </PP>
  </NP>
</root>
