<?xml version="1.0" encoding="UTF-8"?>
<root>
  <world>
    <object name="barrel0" object_type="barrel" object_color="red" position="-0.116208 3.00426 0.270293" orientation="0,0,0,1"/>
    <object name="barrel1" object_type="barrel" object_color="red" position="-0.408732 4.47338 0.270293" orientation="0,0,0,1"/>
    <object name="barrel2" object_type="barrel" object_color="red" position="-0.854003 6.74568 0.270293" orientation="0,0,0,1"/>
    <object name="barrel3" object_type="barrel" object_color="red" position="0.369839 7.5787 0.270293" orientation="0,0,0,1"/>
    <object name="chair0" object_type="chair" object_color="white" position="-7.58763 -4.77037 0.01" orientation="0,0,0,1"/>
    <object name="chair1" object_type="chair" object_color="white" position="-5.16792 -7.14781 0.01" orientation="0,0,0,1"/>
    <object name="chair2" object_type="chair" object_color="white" position="-5.12333 -1.6863 0.01" orientation="0,0,0,1"/>
    <object name="chair3" object_type="chair" object_color="white" position="-3.61261 -5.91587 0.01" orientation="0,0,0,1"/>
    <object name="chair4" object_type="chair" object_color="white" position="-2.97806 -2.92712 0.01" orientation="0,0,0,1"/>
    <object name="cone0" object_type="cone" object_color="orange" position="4.68745 -5.25788 0.00962007" orientation="0,0,0,1"/>
    <object name="cone1" object_type="cone" object_color="orange" position="4.74737 -3.06095 0.00962007" orientation="0,0,0,1"/>
    <object name="cone2" object_type="cone" object_color="orange" position="4.38656 -0.838994 0.00962007" orientation="0,0,0,1"/>
    <object name="cone3" object_type="cone" object_color="orange" position="4.22332 1.20469 0.00962007" orientation="0,0,0,1"/>
    <object name="ground" object_type ="ground" object_color="na" position="0 0 0" orientation="0,0,0,1"/>
    <object name="husky_mm" object_type="robot" object_color="na" position="0.369435 -0.010466 0.38539" orientation="0,0,0,1"/>
  </world>
</root>
